cromosim/__init__.py
cromosim/ca.py
cromosim/comp.py
cromosim/domain.py
cromosim/domain_test.py
cromosim/ftl.py
cromosim/micro.py
cromosim/version.py
cromosim-2.1.0.dist-info/LICENSE
cromosim-2.1.0.dist-info/METADATA
cromosim-2.1.0.dist-info/WHEEL
cromosim-2.1.0.dist-info/top_level.txt
cromosim-2.1.0.dist-info/RECORD
