Metadata-Version: 2.1
Name: cromosim
Version: 2.1.0
Home-page: http://www.cromosim.fr
Author: Sylvain Faure, Bertrand Maury
Author-email: sylvain.faure@math.u-psud.fr, bertrand.maury@math.u-psud.fr
License: GPL
Keywords: Crowd Motion Simulator
Classifier: Development Status :: 5 - Production/Stable
Classifier: Intended Audience :: Education
Classifier: Intended Audience :: Science/Research
Classifier: Intended Audience :: Developers
Classifier: License :: OSI Approved :: GNU Lesser General Public License v3 or later (LGPLv3+)
Classifier: Programming Language :: Python :: 3.5
Classifier: Programming Language :: Python :: 3.6
Classifier: Programming Language :: Python :: 3.7
Classifier: Topic :: Software Development
Classifier: Topic :: Scientific/Engineering
Classifier: Operating System :: Microsoft :: Windows
Classifier: Operating System :: Unix
Classifier: Operating System :: MacOS
Classifier: Topic :: Scientific/Engineering :: Mathematics
Classifier: Topic :: Software Development :: Libraries :: Python Modules
License-File: LICENSE
Requires-Dist: numpy
Requires-Dist: scipy
Requires-Dist: Pillow
Requires-Dist: matplotlib
Requires-Dist: numpydoc
Requires-Dist: sphinx
Requires-Dist: scikit-fmm
Requires-Dist: cvxopt
Requires-Dist: imageio
Requires-Dist: pytest
